LICENSE
MANIFEST.in
README.md
requirements.txt
setup.cfg
setup.py
gevent_tasks/__init__.py
gevent_tasks/manager.py
gevent_tasks/tasks.py
gevent_tasks/utils.py
gevent_tasks.egg-info/PKG-INFO
gevent_tasks.egg-info/SOURCES.txt
gevent_tasks.egg-info/dependency_links.txt
gevent_tasks.egg-info/requires.txt
gevent_tasks.egg-info/top_level.txt