Metadata-Version: 1.1
Name: gevent-tasks
Version: 0.1.6
Summary: Background task management using gevent and green threads.
Home-page: https://github.com/blakev/gevent-tasks
Author: Blake VandeMerwe
Author-email: blakev@null.net
License: UNKNOWN
Platform: any
Classifier: Topic :: Software Development :: Libraries
Classifier: Natural Language :: English
Classifier: License :: OSI Approved :: MIT License
Classifier: Intended Audience :: Developers
Classifier: Development Status :: 4 - Beta
Classifier: Programming Language :: Python
Classifier: Programming Language :: Python :: 3.6
